{
 "kind": "books#volumes",
 "totalItems": 518,
 "items": [
  {
   "kind": "books#volume",
   "id": "061QAAAAMAAJ",
   "etag": "ncBioGB0/uI",
   "selfLink": "https://www.googleapis.com/books/v1/volumes/061QAAAAMAAJ",
   "volumeInfo": {
    "title": "Applied Perl",
    "authors": [
     "Peter Williams"
    ],
    "publisher": "John Wiley & Sons Inc",
    "publishedDate": "2001-05",
    "industryIdentifiers": [
     {
      "type": "ISBN_10",
      "identifier": "0764547836"
     },
     {
      "type": "ISBN_13",
      "identifier": "9780764547836"
     }
    ],
    "pageCount": 405,
    "printType": "BOOK",
    "categories": [
     "Computers"
    ],
    "contentVersion": "preview-1.0.0",
    "imageLinks": {
     "smallThumbnail": "http://bks3.books.google.com/books?id=061QAAAAMAAJ&printsec=frontcover&img=1&zoom=5&source=gbs_api",
     "thumbnail": "http://bks3.books.google.com/books?id=061QAAAAMAAJ&printsec=frontcover&img=1&zoom=1&source=gbs_api"
    },
    "language": "en",
    "previewLink": "http://books.google.com/books?id=061QAAAAMAAJ&q=perl&dq=perl&ie=ISO-8859-1&cd=87&source=gbs_api",
    "infoLink": "http://books.google.com/books?id=061QAAAAMAAJ&dq=perl&ie=ISO-8859-1&source=gbs_api"
   },
   "saleInfo": {
    "country": "US",
    "saleability": "NOT_FOR_SALE",
    "isEbook": false
   },
   "accessInfo": {
    "country": "US",
    "viewability": "NO_PAGES",
    "embeddable": false,
    "publicDomain": false,
    "textToSpeechPermission": "ALLOWED_FOR_ACCESSIBILITY",
    "accessViewStatus": "NONE"
   }
  }
 ]
}
